title_detection/__init__.py
title_detection/deep_nn.py
title_detection/inference.py
title_detection/model_loader.py
title_detection/preprocess.py
title_detection/train.py
title_detection-0.2.dist-info/METADATA
title_detection-0.2.dist-info/WHEEL
title_detection-0.2.dist-info/top_level.txt
title_detection-0.2.dist-info/RECORD
